{
  "decisions": {
    "1179|@babel/cli>chokidar>fsevents>node-pre-gyp>mkdirp>minimist": {
      "decision": "ignore",
      "madeAt": 1586934777267,
      "expiresAt": 1589526742315
    },
    "1179|@vue/cli-plugin-eslint>webpack>watchpack>chokidar>fsevents>node-pre-gyp>mkdirp>minimist": {
      "decision": "ignore",
      "madeAt": 1586934777267,
      "expiresAt": 1589526742315
    },
    "1179|@vue/cli-service>webpack>watchpack>chokidar>fsevents>node-pre-gyp>mkdirp>minimist": {
      "decision": "ignore",
      "madeAt": 1586934777267,
      "expiresAt": 1589526742315
    },
    "1179|webpack>watchpack>chokidar>fsevents>node-pre-gyp>mkdirp>minimist": {
      "decision": "ignore",
      "madeAt": 1586934777267,
      "expiresAt": 1589526742315
    },
    "1179|@vue/cli-service>webpack-dev-server>chokidar>fsevents>node-pre-gyp>mkdirp>minimist": {
      "decision": "ignore",
      "madeAt": 1586934777267,
      "expiresAt": 1589526742315
    },
    "1179|@babel/cli>chokidar>fsevents>node-pre-gyp>tar>mkdirp>minimist": {
      "decision": "ignore",
      "madeAt": 1586934777267,
      "expiresAt": 1589526742315
    },
    "1179|@vue/cli-plugin-eslint>webpack>watchpack>chokidar>fsevents>node-pre-gyp>tar>mkdirp>minimist": {
      "decision": "ignore",
      "madeAt": 1586934777267,
      "expiresAt": 1589526742315
    },
    "1179|@vue/cli-service>webpack>watchpack>chokidar>fsevents>node-pre-gyp>tar>mkdirp>minimist": {
      "decision": "ignore",
      "madeAt": 1586934777267,
      "expiresAt": 1589526742315
    },
    "1179|webpack>watchpack>chokidar>fsevents>node-pre-gyp>tar>mkdirp>minimist": {
      "decision": "ignore",
      "madeAt": 1586934777267,
      "expiresAt": 1589526742315
    },
    "1179|@vue/cli-service>webpack-dev-server>chokidar>fsevents>node-pre-gyp>tar>mkdirp>minimist": {
      "decision": "ignore",
      "madeAt": 1586934777267,
      "expiresAt": 1589526742315
    },
    "1179|@babel/cli>chokidar>fsevents>node-pre-gyp>rc>minimist": {
      "decision": "ignore",
      "madeAt": 1586934777267,
      "expiresAt": 1589526742315
    },
    "1179|@vue/cli-plugin-eslint>webpack>watchpack>chokidar>fsevents>node-pre-gyp>rc>minimist": {
      "decision": "ignore",
      "madeAt": 1586934777267,
      "expiresAt": 1589526742315
    },
    "1179|@vue/cli-service>webpack>watchpack>chokidar>fsevents>node-pre-gyp>rc>minimist": {
      "decision": "ignore",
      "madeAt": 1586934777267,
      "expiresAt": 1589526742315
    },
    "1179|webpack>watchpack>chokidar>fsevents>node-pre-gyp>rc>minimist": {
      "decision": "ignore",
      "madeAt": 1586934777267,
      "expiresAt": 1589526742315
    },
    "1179|@vue/cli-service>webpack-dev-server>chokidar>fsevents>node-pre-gyp>rc>minimist": {
      "decision": "ignore",
      "madeAt": 1586934777267,
      "expiresAt": 1589526742315
    },
    "1488|prettier-eslint>vue-eslint-parser>espree>acorn": {
      "decision": "ignore",
      "madeAt": 1586934955065,
      "expiresAt": 1589526946034
    }
  },
  "rules": {},
  "version": 1
}